FoccoERPy/__init__.py
FoccoERPy/exceptions.py
FoccoERPy/handlers.py
FoccoERPy-1.0.0.dist-info/LICENSE
FoccoERPy-1.0.0.dist-info/METADATA
FoccoERPy-1.0.0.dist-info/WHEEL
FoccoERPy-1.0.0.dist-info/top_level.txt
FoccoERPy-1.0.0.dist-info/RECORD
